pyargus/__init__.py
pyargus/api.py
pyargus/client.py
pyargus/models.py
argus_api_client-0.6.0.dist-info/LICENSE
argus_api_client-0.6.0.dist-info/METADATA
argus_api_client-0.6.0.dist-info/WHEEL
argus_api_client-0.6.0.dist-info/top_level.txt
argus_api_client-0.6.0.dist-info/RECORD
